<categories>
    <category>
        <name> Office </name>
        <logic>
            <desktop_category> office </desktop_category>
        </logic>
    </category>
    <category>
        <name> Development </name>
        <logic>
            <desktop_category> development </desktop_category>
        </logic>
    </category>
    <category>
        <name> Network</name>
        <logic>
            <or>
                <desktop_category> network </desktop_category>
                <desktop_id> com.ubuntu1904.firefox.desktop </desktop_id>
            <desktop_category> communication </desktop_category>
            <desktop_category> IRCClient </desktop_category>
            <desktop_category> InstantMessaging </desktop_category>
            </or>
        </logic>
    </category>
    <category>
        <name> Graphics </name>
        <logic>
            <or>
                <desktop_category> graphics </desktop_category>
                <desktop_category> photography </desktop_category>
            </or>
        </logic>
    </category>
    <category>
        <name> Multimedia </name>
        <logic>
            <or>
                <desktop_category> audiovideo </desktop_category>
                <desktop_category> audio </desktop_category>
                <desktop_category> player </desktop_category>
            </or>
        </logic>
    </category>
    <category>
        <name> Utilities </name>
        <logic>
            <desktop_category> utility </desktop_category>
        </logic>
    </category>
    <category>
        <name> Settings </name>
        <logic>
            <desktop_category> settings </desktop_category>
        </logic>
    </category>
    <category>
        <name> Others </name>
        <repeat> false </repeat>
        <logic>
            <all></all>
        </logic>
    </category>
</categories>